{"issues": [
  {
    "id": 1,
    "title": "Title 1",
    "desc": "Lorem ipsum dolor sit amet consectetur, adipisicing elit. Expedita doloremque cum cupiditate excepturi? Blanditiis, laboriosam.",
    "createdAt": "2022-10-22T11_01_01",
    "completed": false,
    "user": "Emil Lind"
  },
  {
    "id": 2,
    "title": "Title 2",
    "desc": "Lorem ipsum dolor sit amet consectetur, adipisicing elit. Expedita doloremque cum cupiditate excepturi? Blanditiis, laboriosam.",
    "createdAt": "2022-10-22T11_01_01",
    "completed": false,
    "user": "Emil Lind"
  },
  {
    "id": 3,
    "title": "Title 3",
    "desc": "Lorem ipsum dolor sit amet consectetur, adipisicing elit. Expedita doloremque cum cupiditate excepturi? Blanditiis, laboriosam.",
    "createdAt": "2022-10-22T11_01_01",
    "completed": true,
    "user": "Emil Lind"
  }
]

}